clrc/__init__.py
clrc/lib.py
clrc/exceptions/__init__.py
clrc/exceptions/invalid_printer_exception.py
clrc/printers/__init__.py
clrc/printers/abstract_printer.py
clrc/printers/colorama_stdout_printer.py
clrc/printers/loguru_printer.py
clrc-0.0.6.dist-info/LICENCE.md
clrc-0.0.6.dist-info/METADATA
clrc-0.0.6.dist-info/WHEEL
clrc-0.0.6.dist-info/top_level.txt
clrc-0.0.6.dist-info/RECORD
