Metadata-Version: 2.1
Name: clrc
Version: 0.0.6
Summary: Easy to use console prints with colors. clrc.info(), clrc.success() etc
Home-page: https://github.com/idchlife/clrc
Author: Igor Andreev
Author-email: idchlife@gmail.com
Classifier: Programming Language :: Python :: 3
Classifier: License :: OSI Approved :: MIT License
Classifier: Operating System :: OS Independent
License-File: LICENCE.md
Requires-Dist: colorama (==0.4.5)
